dsg/CNN_classifier.py
dsg/RNN_MTM_classifier.py
dsg/RNN_MTO_classifier.py
dsg/__init__.py
dsg/topic_detection.py
dsg/base/__init__.py
dsg/base/_base.py
dsg/layers/__init__.py
dsg/layers/_cnn_layers.py
dsg/layers/_rnn_layers.py
ds_gear-0.1.303.dist-info/LICENSE
ds_gear-0.1.303.dist-info/METADATA
ds_gear-0.1.303.dist-info/WHEEL
ds_gear-0.1.303.dist-info/dependency_links.txt
ds_gear-0.1.303.dist-info/top_level.txt
ds_gear-0.1.303.dist-info/RECORD
