Metadata-Version: 2.1
Name: ds-gear
Version: 0.1.303
Summary: Data science gear: Python API for advanced machine learning algorithms built on top of sklearn, tensorflow and keras
Home-page: https://github.com/AI-Companion/ds-gear
Author: Marouen Azzouz, Youssef Azzouz
Author-email: azzouz.marouen@gmail.com, youssef.azzouz1512@gmail.com
License: UNKNOWN
Keywords: machine learning recurrent convolutional neural network named entity recognition sentiment analysis deep learning topic detection
Platform: UNKNOWN
Classifier: Programming Language :: Python :: 3.6
Classifier: Development Status :: 3 - Alpha
Classifier: License :: OSI Approved :: MIT License
Classifier: Operating System :: OS Independent
Requires-Python: >=3.6
Requires-Dist: numpy
Requires-Dist: pandas
Requires-Dist: scikit-learn
Requires-Dist: matplotlib
Requires-Dist: pylint
Requires-Dist: doxypypy
Requires-Dist: seaborn
Requires-Dist: pycodestyle
Requires-Dist: opencv-python
Requires-Dist: nltk (==3.5)
Requires-Dist: keras
Requires-Dist: tensorflow
